suprasupromath/__init__.py
suprasupromath/module1.py
suprasupromath-0.0.1.dist-info/licenses/LICENSE
suprasupromath-0.0.1.dist-info/METADATA
suprasupromath-0.0.1.dist-info/WHEEL
suprasupromath-0.0.1.dist-info/top_level.txt
suprasupromath-0.0.1.dist-info/RECORD
