Metadata-Version: 2.4
Name: suprasupromath
Version: 0.0.1
Summary: A super simple math utility package for example purposes.
Author-email: skeptofox <skeptofox@gmail.com>
Project-URL: Homepage, https://github.com/skeptofox/suprasupromath
Project-URL: Issues, https://github.com/skeptofox/suprasupromath/issues
Keywords: math,example,tutorial
Classifier: Programming Language :: Python :: 3
Classifier: License :: OSI Approved :: MIT License
Classifier: Operating System :: OS Independent
Requires-Python: >=3.8
License-File: LICENSE
Dynamic: license-file
